djangofwd_news_simple-0.1.4.dist-info/DESCRIPTION.rst
djangofwd_news_simple-0.1.4.dist-info/METADATA
djangofwd_news_simple-0.1.4.dist-info/metadata.json
djangofwd_news_simple-0.1.4.dist-info/RECORD
djangofwd_news_simple-0.1.4.dist-info/top_level.txt
djangofwd_news_simple-0.1.4.dist-info/WHEEL
news/admin.py
news/cms_app.py
news/models.py
news/tests.py
news/translation.py
news/urls.py
news/views.py
news/__init__.py
news/migrations/0001_initial.py
news/migrations/0001_initial.pyc
news/migrations/__init__.py
news/migrations/__init__.pyc
news/templates/news/news_content.html
news/templates/news/news_detail.html
news/templates/news/news_list.html
news/templates/news/categories/news_content_category.html
news/templates/news/categories/news_detail_category.html
news/templates/news/categories/news_list_categories.html
news/templates/news/categories/news_list_category.html
news/templates/news/templatetags/highlight_news.html
news/templates/news/templatetags/latest_news.html
news/templates/news/templatetags/templatetags_news_content.html
news/templatetags/news_tags.py
news/templatetags/news_tags.pyc
news/templatetags/__init__.py
news/templatetags/__init__.pyc
