Metadata-Version: 2.0
Name: djangofwd-news-simple
Version: 0.1.4
Summary: A simple Django app to conduct Web-based news.
Home-page: http://www.fwd.hr/
Author: Daniele Milani
Author-email: daniele@fwd.hr
License: MIT
Keywords: News fwd simple development
Platform: UNKNOWN
Classifier: Environment :: Web Environment
Classifier: Framework :: Django
Classifier: Intended Audience :: Developers
Classifier: License :: OSI Approved :: MIT License
Classifier: Operating System :: OS Independent
Classifier: Programming Language :: Python
Classifier: Programming Language :: Python :: 2
Classifier: Programming Language :: Python :: 2.6
Classifier: Programming Language :: Python :: 2.7
Classifier: Topic :: Internet :: WWW/HTTP
Classifier: Topic :: Internet :: WWW/HTTP :: Dynamic Content
Requires-Dist: django-classy-tags (==0.6.1)
Requires-Dist: django-modeltranslation (==0.8.1)
Requires-Dist: easy-thumbnails (==2.2)
Requires-Dist: Pillow (==2.8.1)
Requires-Dist: pytz (==2015.2)
